agentsage-0.1.2.dist-info/licenses/LICENSE
sage/__init__.py
sage/cli.py
sage/core.py
sage/py.typed
sage/types.py
sage/agents/__init__.py
sage/agents/base.py
sage/agents/nodes.py
sage/graph/__init__.py
sage/graph/state.py
sage/graph/workflow.py
sage/providers/__init__.py
sage/providers/factory.py
sage/tools/__init__.py
sage/tools/code_exec.py
sage/tools/file_reader.py
sage/tools/web_search.py
agentsage-0.1.2.dist-info/METADATA
agentsage-0.1.2.dist-info/WHEEL
agentsage-0.1.2.dist-info/entry_points.txt
agentsage-0.1.2.dist-info/top_level.txt
agentsage-0.1.2.dist-info/RECORD
