Metadata-Version: 2.4
Name: agentsage
Version: 0.1.2
Summary: SAGE: Synchronized Agents for Generalized Expertise - A multi-agent framework where AI agents research, debate, and synthesize answers together
Author: SAGE Contributors
Maintainer: SAGE Contributors
License: MIT
Project-URL: Homepage, https://github.com/najmulhasan-code/sage
Project-URL: Documentation, https://github.com/najmulhasan-code/sage#readme
Project-URL: Repository, https://github.com/najmulhasan-code/sage.git
Project-URL: Issues, https://github.com/najmulhasan-code/sage/issues
Project-URL: Changelog, https://github.com/najmulhasan-code/sage/releases
Keywords: multi-agent,llm,ai-agents,collaboration,openai,anthropic,langgraph,langchain,gpt-4,claude,gemini,reasoning,debate,research,synthesis,agentic-ai
Classifier: Development Status :: 4 - Beta
Classifier: Intended Audience :: Developers
Classifier: Intended Audience :: Science/Research
Classifier: License :: OSI Approved :: MIT License
Classifier: Operating System :: OS Independent
Classifier: Programming Language :: Python :: 3
Classifier: Programming Language :: Python :: 3.10
Classifier: Programming Language :: Python :: 3.11
Classifier: Programming Language :: Python :: 3.12
Classifier: Programming Language :: Python :: 3.13
Classifier: Topic :: Scientific/Engineering :: Artificial Intelligence
Classifier: Topic :: Software Development :: Libraries :: Python Modules
Classifier: Typing :: Typed
Requires-Python: >=3.10
License-File: LICENSE
Requires-Dist: langgraph>=0.2.0
Requires-Dist: langchain>=0.3.0
Requires-Dist: langchain-core>=0.3.0
Requires-Dist: langchain-openai>=0.2.0
Requires-Dist: langchain-community>=0.3.0
Requires-Dist: langchain-experimental>=0.3.0
Requires-Dist: ddgs>=9.0.0
Requires-Dist: python-dotenv>=1.0.0
Requires-Dist: pydantic>=2.0.0
Requires-Dist: rich>=13.0.0
Provides-Extra: anthropic
Requires-Dist: langchain-anthropic>=0.2.0; extra == "anthropic"
Provides-Extra: google
Requires-Dist: langchain-google-genai>=2.0.0; extra == "google"
Provides-Extra: ollama
Requires-Dist: langchain-ollama>=0.2.0; extra == "ollama"
Provides-Extra: aws
Requires-Dist: langchain-aws>=0.2.0; extra == "aws"
Provides-Extra: all
Requires-Dist: langchain-anthropic>=0.2.0; extra == "all"
Requires-Dist: langchain-google-genai>=2.0.0; extra == "all"
Requires-Dist: langchain-ollama>=0.2.0; extra == "all"
Requires-Dist: langchain-aws>=0.2.0; extra == "all"
Provides-Extra: dev
Requires-Dist: pytest>=8.0.0; extra == "dev"
Requires-Dist: pytest-asyncio>=0.23.0; extra == "dev"
Requires-Dist: pytest-cov>=4.0.0; extra == "dev"
Requires-Dist: black>=24.0.0; extra == "dev"
Requires-Dist: ruff>=0.3.0; extra == "dev"
Requires-Dist: mypy>=1.8.0; extra == "dev"
Requires-Dist: pre-commit>=3.6.0; extra == "dev"
Dynamic: license-file
